tkdata/__init__.py
tkdata/tkdata.py
tkdata-0.0.4.dist-info/LICENSE
tkdata-0.0.4.dist-info/METADATA
tkdata-0.0.4.dist-info/WHEEL
tkdata-0.0.4.dist-info/top_level.txt
tkdata-0.0.4.dist-info/RECORD
