Metadata-Version: 2.1
Name: tkdata
Version: 0.0.4
Summary: Create tkinter forms easily
Home-page: https://github.com/aFelipeSP/tkdata
Author: Andrés Felipe Sierra Parra
Author-email: cepfelo@gmail.com
License: UNKNOWN
Platform: UNKNOWN
Classifier: Programming Language :: Python :: 3
Classifier: License :: OSI Approved :: MIT License
Classifier: Operating System :: OS Independent
Requires-Python: >=3.4
